rfclint/CursesCommon.py
rfclint/__init__.py
rfclint/abnf.py
rfclint/config.py
rfclint/dups.py
rfclint/must.py
rfclint/run.py
rfclint/sitecustomize.py
rfclint/spell.py
rfclint/test.py
rfclint-1.0.0.dist-info/licenses/LICENSE
rfclint-1.0.0.dist-info/METADATA
rfclint-1.0.0.dist-info/WHEEL
rfclint-1.0.0.dist-info/entry_points.txt
rfclint-1.0.0.dist-info/top_level.txt
rfclint-1.0.0.dist-info/RECORD
