Metadata-Version: 2.4
Name: rfclint
Version: 1.0.0
Summary: Perform a set of checks on an RFC input file to check for errors.
Author-email: IETF Tools <tools-help@ietf.org>
License-Expression: BSD-3-Clause
Project-URL: homepage, https://github.com/ietf-tools/rfclint
Project-URL: source, https://github.com/ietf-tools/rfclint
Project-URL: issues, https://github.com/ietf-tools/rfclint/issues
Project-URL: changelog, https://github.com/ietf-tools/rfclint/blob/main/CHANGELOG.md
Project-URL: releasenotes, https://github.com/ietf-tools/rfclint/releases
Keywords: validation,rfc,internet-draft
Classifier: Development Status :: 3 - Alpha
Classifier: Environment :: Console
Classifier: Intended Audience :: Other Audience
Classifier: Topic :: Text Processing
Classifier: Topic :: Text Processing :: Markup :: XML
Classifier: Operating System :: MacOS :: MacOS X
Classifier: Operating System :: Microsoft :: Windows
Classifier: Operating System :: POSIX :: Linux
Classifier: Programming Language :: Python :: 2.7
Classifier: Programming Language :: Python :: 3.6
Classifier: Programming Language :: Python :: 3.7
Requires-Python: >=2.7
License-File: LICENSE
Requires-Dist: lxml>=4.1.1
Requires-Dist: requests>=2.5.0
Requires-Dist: six
Requires-Dist: xml2rfc>=3.24.0
Requires-Dist: colorama
Requires-Dist: appdirs
Requires-Dist: svgcheck>=0.6.0
Provides-Extra: tests
Requires-Dist: coverage; extra == "tests"
Requires-Dist: flake8; extra == "tests"
Requires-Dist: tox; extra == "tests"
Dynamic: license-file
